fire_challenge/__init__.py
fire_challenge/challenge_maps.py
fire_challenge/fire_challenge.py
fire_challenge-2.0.1.dist-info/METADATA
fire_challenge-2.0.1.dist-info/WHEEL
fire_challenge-2.0.1.dist-info/RECORD
