Metadata-Version: 2.4
Name: fire-challenge
Version: 2.0.1
Summary: A Python module for grid-based fire spread challenges
Project-URL: Homepage, https://github.com/PeterTheobald/HackerDojoPythonGroup/tree/main/fire_challenge
Project-URL: Repository, https://github.com/PeterTheobald/HackerDojoPythonGroup/tree/main/fire_challenge
Project-URL: Issues, https://github.com/PeterTheobald/HackerDojoPythonGroup/issues
Author-email: Peter Theobald <PeterTheobald@users.noreply.github.com>
License: MIT
Keywords: challenge,education,game,learning,programming
Classifier: Development Status :: 4 - Beta
Classifier: Intended Audience :: Education
Classifier: Programming Language :: Python :: 3
Classifier: Programming Language :: Python :: 3.10
Classifier: Programming Language :: Python :: 3.11
Classifier: Programming Language :: Python :: 3.12
Classifier: Topic :: Education
Requires-Python: >=3.10
Requires-Dist: matplotlib>=3.7.0
Requires-Dist: numpy>=1.24.0
